<?xml version="1.0" encoding="UTF-8"?>
<tsl xmlns="http://www.dexels.com/navascript" xmlns:xsi="http://www.w3.org/2001/XMLSchema-instance"
    xsi:schemaLocation="http://www.dexels.com/navascript http://www.dexels.nl:8080/schema/navascript.xsd">
    <map object="com.dexels.navajo.adapter.AdminMap">
        <field name="collectGarbage">
            <expression value="true"/>
        </field>
    </map>
    <map object="com.dexels.navajo.adapter.NavajoMap">
        <field name="doSend">
           <expression value="'navajo/ProcessGetMemoryStatus'"/>
        </field>
        <field name="append">
           <expression value="''"/>
        </field> 
    </map> 
</tsl>
